orgtreepubsub/__init__.py
orgtreepubsub/conftest.py
orgtreepubsub/orgtreepubsub.py
orgtreepubsub/py.typed
orgtreepubsub/test_crawl_no_org.py
orgtreepubsub/test_crawl_organization.py
orgtreepubsub/type_defs.py
orgtreepubsub-0.1.0.dist-info/METADATA
orgtreepubsub-0.1.0.dist-info/WHEEL
orgtreepubsub-0.1.0.dist-info/entry_points.txt
orgtreepubsub-0.1.0.dist-info/RECORD
